{
  "skill_name": "QA",
  "description": "Тестирование программного обеспечения: manual, automation, performance, security testing",
  "levels": {
    "1": [
      {
        "id": "qa_1_1",
        "marker": "Составил тест‑план и тест‑кейсы для функциональности приложения (10+ кейсов, покрытие happy path и edge cases)",
        "validation": "Документ тест‑плана, таблица тест‑кейсов с шагами и ожидаемыми результатами",
        "priority": "high",
        "resources": ["https://www.guru99.com/test-plan.html"],
        "smart_criteria": {
          "specific": "Создать тест‑план и тест‑кейсы",
          "measurable": "10+ тест‑кейсов, покрытие основных сценариев и boundary values",
          "achievable": "Уровень начинающего",
          "relevant": "Требуется для системного тестирования",
          "time_bound": "2 дня"
        },
        "methodology_author": "Ekaterina Kudelya",
        "methodology_license": "CC BY-ND 4.0"
      },
      {
        "id": "qa_1_2",
        "marker": "Выполнил manual testing, завел баг‑репорты в трекере (Jira, GitHub Issues) с четким описанием шагов воспроизведения, ожидаемого/фактического результата",
        "validation": "Список баг‑репортов, скриншоты/видео, приоритизация",
        "priority": "medium",
        "resources": ["https://www.atlassian.com/software/jira"],
        "smart_criteria": {
          "specific": "Провести manual testing и завести баг‑репорты",
          "measurable": "5+ баг‑репортов с воспроизводимыми шагами, severity/priority",
          "achievable": "Уроволь начинающего",
          "relevant": "Необходимо для выявления дефектов",
          "time_bound": "1 день"
        },
        "methodology_author": "Ekaterina Kudelya",
        "methodology_license": "CC BY-ND 4.0"
      }
    ],
    "2": [
      {
        "id": "qa_2_1",
        "marker": "Написал автоматизированные UI‑тесты (Selenium, Cypress, Playwright) для критического пути приложения",
        "validation": "Код автотестов, отчет о прогоне, скриншоты/видео прохождения",
        "priority": "high",
        "resources": ["https://www.cypress.io/"],
        "smart_criteria": {
          "specific": "Создать набор автоматизированных UI‑тестов",
          "measurable": "5+ автотестов, покрытие critical path, стабильность прогона > 90%",
          "achievable": "Уровень средний",
          "relevant": "Требуется для регрессионного тестирования",
          "time_bound": "2 недели"
        },
        "methodology_author": "Ekaterina Kudelya",
        "methodology_license": "CC BY-ND 4.0"
      }
    ],
    "3": [
      {
        "id": "qa_3_1",
        "marker": "Провел нагрузочное тестирование (JMeter, k6) и проанализировал bottlenecks (CPU, memory, DB, network)",
        "validation": "Скрипты нагрузочного тестирования, графики метрик (RPS, latency, error rate), рекомендации по оптимизации",
        "priority": "medium",
        "resources": ["https://k6.io/"],
        "smart_criteria": {
          "specific": "Выполнить нагрузочное тестирование и выявить bottlenecks",
          "measurable": "Определены пределы производительности (макс. RPS), выявлены 3+ узких места, даны рекомендации",
          "achievable": "Продвинутый уровень",
          "relevant": "Критично для обеспечения стабильности под нагрузкой",
          "time_bound": "3 недели"
        },
        "methodology_author": "Ekaterina Kudelya",
        "methodology_license": "CC BY-ND 4.0"
      }
    ]
  }
}
